mearul1/A1.py
mearul1/A10.py
mearul1/A2.py
mearul1/A3.py
mearul1/A4.py
mearul1/A5.py
mearul1/A6.py
mearul1/A7.py
mearul1/A8.py
mearul1/A9.py
mearul1/__init__.py
mearul1/helpers.py
mearul1-1.0.0.dist-info/licenses/LICENSE.txt
mearul1-1.0.0.dist-info/METADATA
mearul1-1.0.0.dist-info/WHEEL
mearul1-1.0.0.dist-info/top_level.txt
mearul1-1.0.0.dist-info/RECORD
