Metadata-Version: 2.4
Name: mearul1
Version: 1.0.0
Summary: Encrypted Python files package for Jupyter Notebook
Author: Justin Mearul
Author-email: yoyoyo@gmail.com
Requires-Python: >=3.8
License-File: LICENSE.txt
Requires-Dist: cryptography
Dynamic: author
Dynamic: author-email
Dynamic: license-file
Dynamic: requires-dist
Dynamic: requires-python
Dynamic: summary
